LICENSE
MANIFEST.in
README.md
setup.py
streaming/__init__.py
streaming/_cython.c
streaming/_cython.pyx
streaming/_iterator.py
streaming/abstractstream.py
streaming/itertools.py
streaming/operators.py
streaming/signal.py
streaming/stream.py
streaming.egg-info/PKG-INFO
streaming.egg-info/SOURCES.txt
streaming.egg-info/dependency_links.txt
streaming.egg-info/not-zip-safe
streaming.egg-info/requires.txt
streaming.egg-info/top_level.txt