Metadata-Version: 1.1
Name: streaming
Version: 0.1.2
Summary: Streaming data with Python
Home-page: UNKNOWN
Author: Frederik Rietdijk
Author-email: freddyrietdijk@fridh.nl
License: LICENSE
Platform: UNKNOWN
Classifier: License :: OSI Approved :: BSD License
Classifier: Programming Language :: Cython
Classifier: Programming Language :: Python :: 3 :: Only
Classifier: Programming Language :: Python :: 3.5
Classifier: Topic :: Scientific/Engineering
